waybackshot/__init__.py
waybackshot/helpers.py
waybackshot/waybackshot.py
waybackshot-0.2.1.dist-info/LICENSE
waybackshot-0.2.1.dist-info/METADATA
waybackshot-0.2.1.dist-info/WHEEL
waybackshot-0.2.1.dist-info/top_level.txt
waybackshot-0.2.1.dist-info/RECORD
